{"palette":[0,198,5,6],"select-glow":[170,194,16,18],"icon-ice":[180,214,10,10],"icon8-sword":[92,140,8,8],"select-cursor":[206,140,17,17],"icon6-hat":[183,97,6,6],"icon6-dagger":[182,178,6,6],"tag":[223,140,5,12],"select-arrows":[120,0,64,64],"icon6-shield":[190,214,6,6],"icon6-bow":[184,34,6,6],"icon-fire":[184,24,10,10],"icon8-axe":[220,77,8,8],"font-serif":[0,0,120,77],"icon-volt":[216,0,10,10],"icon6-cudgel":[194,24,6,6],"icon-dark":[180,64,10,10],"font-six":[0,176,50,12],"buttons":[0,140,54,36],"font-smallcaps":[170,77,50,20],"font-smallcaps-radiant":[100,214,80,14],"bars":[100,140,68,27],"font-numbers":[120,64,60,12],"icon8-shield":[74,178,8,8],"icon8-dagger":[206,157,8,8],"font-standard":[100,77,70,63],"hp":[54,140,38,38],"icon8-hat":[186,194,8,8],"labels":[170,97,13,18],"icon6-sword":[216,10,6,6],"icon8-bow":[170,115,8,8],"piece":[168,178,14,14],"icon-holy":[0,188,10,10],"font-standard-bold":[0,77,100,63],"icon-plant":[54,198,10,10],"vs":[168,140,38,38],"icon6-axe":[190,64,6,6],"bar":[100,167,68,27],"select-ring":[54,178,20,20],"font-smallcaps-bold":[100,194,70,20],"badges":[184,0,32,24]}